CHANGES.txt
MANIFEST.in
README.md
setup.cfg
setup.py
hiero/__init__.py
hiero/interfaces.py
hiero/resources.py
hiero/routes.py
hiero.egg-info/PKG-INFO
hiero.egg-info/SOURCES.txt
hiero.egg-info/dependency_links.txt
hiero.egg-info/entry_points.txt
hiero.egg-info/not-zip-safe
hiero.egg-info/requires.txt
hiero.egg-info/top_level.txt
hiero/formatters/__init__.py
hiero/formatters/htmlblock_formatter.py
hiero/formatters/linebreaks.py
hiero/formatters/markdown_formatter.py
hiero/formatters/rst_formatter.py
hiero/forms/__init__.py
hiero/models/__init__.py
hiero/models/blog.py
hiero/models/page.py
hiero/schemas/__init__.py
hiero/schemas/blog.py
hiero/static/assets/css/bootstrap-responsive.css
hiero/static/assets/css/bootstrap-responsive.min.css
hiero/static/assets/css/bootstrap.css
hiero/static/assets/css/bootstrap.min.css
hiero/static/assets/img/glyphicons-halflings-white.png
hiero/static/assets/img/glyphicons-halflings.png
hiero/static/assets/js/bootstrap.js
hiero/static/assets/js/bootstrap.min.js
hiero/static/assets/js/jquery.js
hiero/templates/app_layout.mako
hiero/templates/blog_index.mako
hiero/templates/blog_utilities.mako
hiero/templates/entry_detail.mako
hiero/templates/entry_edit.mako
hiero/templates/index.mako
hiero/templates/layout.mako
hiero/templates/admin/category_index.mako
hiero/templates/admin/edit_category.mako
hiero/templates/admin/edit_entry.mako
hiero/templates/admin/edit_series.mako
hiero/templates/admin/entry_index.mako
hiero/templates/admin/index.mako
hiero/templates/admin/series_index.mako
hiero/templates/page/page_layout.mako
hiero/templates/page/view_add_edit.mako
hiero/templates/widgets/select.pt
hiero/templates/widgets/select_category.pt
hiero/templates/widgets/select_series.pt
hiero/templates/widgets/select_user.pt
hiero/tests/__init__.py
hiero/tests/models.py
hiero/tests/test.ini
hiero/tests/test_interfaces.py
hiero/tests/wsgi_demo.py
hiero/tests/blog/__init__.py
hiero/tests/blog/test_models.py
hiero/tests/blog/test_views.py
hiero/views/__init__.py
hiero/views/blog.py
hiero/views/page.py