Metadata-Version: 1.1
Name: hiero
Version: 0.3.4
Summary: hiero
Home-page: UNKNOWN
Author: John Anderson
Author-email: sontek@gmail.com
License: UNKNOWN
Keywords: web pyramid pylons
Platform: UNKNOWN
Classifier: Programming Language :: Python
Classifier: Framework :: Pylons
Classifier: Topic :: Internet :: WWW/HTTP
Classifier: Topic :: Internet :: WWW/HTTP :: WSGI :: Application
